module/__init__.py
mathmodule14750-0.1.0.dist-info/METADATA
mathmodule14750-0.1.0.dist-info/WHEEL
mathmodule14750-0.1.0.dist-info/top_level.txt
mathmodule14750-0.1.0.dist-info/RECORD
